{
    // From Puma.
    // From the ready-missile count, this seems to be six two-missile TELs.
    "name": "SA-12B",
    "description": "SA-12B air-defense battery",
    "symbols": "air-defense/missile/truck/limitedwheeled/battery",
    "text": "SA-12B",
    "defensestrength": "4H",
    "sightingrange": 12,
    "mobility": "U",
    "sam": {
        "type": "SA-12B",
        "ewrfrequency": "VF",
        "ewrrange": 125,
        "ewrmti": true,
        "ttrfrequency": "VF",
        "ttrrange": 80,
        "multitargetcapability": 6,
        "readymissiles": 12,
        "volleymissiles": 2,
        "radarlockon": 9
    }
}